lcd/ol2.v
module oled_video #(
  // file name is relative to directory path in which verilog compiler is running
  // screen can be also XY flipped and/or rotated from this init file
  parameter C_init_file = "st7735_init.mem",
  parameter C_init_size = 110 // bytes in init file
) (
  input  wire clk, // SPI display clock rate will be half of this clock rate
  
  output reg  [C_x_bits-1:0] x,
  output reg  [C_y_bits-1:0] y,
  output reg  next_pixel, // 1 when x/y changes
  input  wire [C_color_bits-1:0] color, 

  output wire oled_csn,
  output wire oled_clk,
  output wire oled_mosi,
  output wire oled_dc,
  output wire oled_resn
);
  localparam C_color_bits = 16;
  localparam C_x_size = 128;  // pixel X screen size
  localparam C_y_size = 160;  // pixel Y screen size
  localparam C_x_bits = $clog2(C_x_size); 
  localparam C_y_bits = $clog2(C_y_size);

  localparam ms_cycles = 25000;

  reg [7:0] C_oled_init[0:C_init_size-1];
  initial begin
    $readmemh(C_init_file, C_oled_init);
  end

  reg [1:0]  reset_cnt;
  reg [10:0] init_cnt;
  reg [7:0]  data;
  reg dc;
  reg byte_toggle; // alternates data byte for 16-bit mode
  reg init = 1;
  reg [4:0] num_args;
  reg [24:0] delay_cnt;
  reg [5:0] arg;
  reg delay_set = 0;
  reg [7:0] last_cmd;
  
  assign oled_resn = ~reset_cnt[0]; // Reset is High, Low, High for first 3 cycles
  assign oled_csn = reset_cnt[0];
  assign oled_dc = dc;              // 0 for commands, 1 for command parameters and data
  assign oled_clk = init_cnt[0];    // SPI Mode 0
  assign oled_mosi = data[7];       // Shift out data

  // The next byte in the initialisation sequence
  wire [7:0] next_byte = C_oled_init[init_cnt[10:4]];

  // Do the initialisation sequence and then start sending pixels
  always @(posedge clk) begin
    if (reset_cnt != 2) begin // Reset
      reset_cnt <= reset_cnt+1;
    end else if (delay_cnt > 0) begin // Delay
      delay_cnt <= delay_cnt - 1;
    end else if (init_cnt[10:4] != C_init_size) begin
      init_cnt <= init_cnt + 1;
      if (init_cnt[3:0] == 0) begin // Start of byte
        if (init) begin // Still initialisation
          dc <= 0;
          arg <= arg + 1;
          if (arg == 0) begin // New command
            data <=  0; // No NOP
            last_cmd <= next_byte;
          end else if (arg == 1) begin // numArgs and delay_set
            num_args <= next_byte[4:0];
            delay_set <= next_byte[7];
            if (next_byte == 0) arg <= 0; // No args or delay
            data <= last_cmd;
          end else if (arg <= num_args + 1) begin // argument
            data <= next_byte;
            dc <= 1;
            if (arg == num_args + 1 && !delay_set) arg <= 0;
          end else if (delay_set) begin // delay
            if (next_byte != 8'hff) begin
              delay_cnt <= next_byte * ms_cycles;
            end else begin // Long delay
              delay_cnt <= 500 * ms_cycles;
            end
            data <= 0;
            delay_set <= 0;
            arg <= 0;
          end
        end else begin // Send pixels and set x,y and next_pixel
          byte_toggle <= ~byte_toggle;
          dc <= 1;
          data <= byte_toggle ? color[7:0] : color[15:8];
          if (byte_toggle == 0) begin
            next_pixel <= 1;
            if (x == C_x_size-1) begin
              x <= 0;
              if (y == C_y_size-1) begin
                y <= 0;
              end else begin
                y <= y + 1;
              end
            end else x <= x + 1;
          end
        end
      end else begin // Shift out byte
        next_pixel <= 0;
        if (init_cnt[0] == 0) data <= { data[6:0], 1'b0 };
      end
    end else begin // Initialisation done, start sending pixels
      init <= 0;
      init_cnt[10:4] <= C_init_size - 1;
    end
  end

endmodule

lcd/top_checkered.v
module top_checkered (
    input  wire clki,
    output wire oled_csn,
    output wire oled_clk,
    output wire oled_mosi,
    output wire oled_dc,
    output wire oled_resn,
    output wire led
);
    //                  checkered      red   green      blue     red       green blue
    wire [15:0] color = x[3] ^ y[3] ? {5'd0, 6'b111111, 5'd0} : {5'b11111, 6'd0, 5'd0};
    wire [6:0] x;
    wire [7:0] y;

    assign led = oled_resn;
    oled_video #(
        .C_init_file("st7735_init.mem"),
        .C_init_size(110)
    ) oled_video_inst (
        .clk(clki),
        .x(x),
        .y(y),
        .color(color),
        .oled_csn(oled_csn),
        .oled_clk(oled_clk),
        .oled_mosi(oled_mosi),
        .oled_dc(oled_dc),
        .oled_resn(oled_resn)
    );

endmodule

lcd/tb.v


module tb;
reg clki;

always #5 clki = (clki === 1'b0);

initial begin
    $dumpfile("testbench.vcd");
    $dumpvars(0, tb);

    repeat (6) begin
        repeat (5000) @(posedge clki);
        $display("+50000 cycles");
    end
    $finish;
end

wire oled_csn;
wire oled_resn;
wire oled_dc;
wire oled_mosi;
wire oled_clk;
wire led_out;

top_checkered dut (.clki(clki),
    .oled_csn(oled_csn),
    .oled_clk(oled_clk),
    .oled_mosi(oled_mosi),
    .oled_dc(oled_dc),
    .oled_resn(oled_resn),
    .led(led)
);

endmodule

lcd/testbench.vcd
$date
	Sun Mar  5 17:02:04 2023
$end
$version
	Icarus Verilog
$end
$timescale
	1s
$end
$scope module tb $end
$var wire 1 ! oled_resn $end
$var wire 1 " oled_mosi $end
$var wire 1 # oled_dc $end
$var wire 1 $ oled_csn $end
$var wire 1 % oled_clk $end
$var wire 1 & led $end
$var reg 1 ' clki $end
$scope module dut $end
$var wire 1 ' clki $end
$var wire 1 & led $end
$var wire 8 ( y [7:0] $end
$var wire 7 ) x [6:0] $end
$var wire 1 ! oled_resn $end
$var wire 1 " oled_mosi $end
$var wire 1 # oled_dc $end
$var wire 1 $ oled_csn $end
$var wire 1 % oled_clk $end
$var wire 16 * color [15:0] $end
$scope module oled_video_inst $end
$var wire 1 ' clk $end
$var wire 16 + color [15:0] $end
$var wire 8 , next_byte [7:0] $end
$var wire 1 # oled_dc $end
$var wire 1 ! oled_resn $end
$var wire 1 " oled_mosi $end
$var wire 1 $ oled_csn $end
$var wire 1 % oled_clk $end
$var reg 6 - arg [5:0] $end
$var reg 1 . byte_toggle $end
$var reg 8 / data [7:0] $end
$var reg 1 0 dc $end
$var reg 25 1 delay_cnt [24:0] $end
$var reg 1 2 delay_set $end
$var reg 1 3 init $end
$var reg 11 4 init_cnt [10:0] $end
$var reg 8 5 last_cmd [7:0] $end
$var reg 1 6 next_pixel $end
$var reg 5 7 num_args [4:0] $end
$var reg 2 8 reset_cnt [1:0] $end
$var reg 8 9 x [7:0] $end
$var reg 7 : y [6:0] $end
$upscope $end
$upscope $end
$upscope $end
$enddefinitions $end
#0
$dumpvars
bx :
bx 9
b0 8
b0 7
x6
bx 5
b0 4
13
02
b0 1
00
b0 /
0.
b0 -
b1 ,
bx00000 +
bx00000 *
bx )
b0xxxxxxx (
x'
1&
0%
0$
0#
0"
1!
$end
#5
0'
#10
0&
0!
1$
b1 8
1'
#15
0'
#20
1&
1!
0$
b10 8
1'
#25
0'
#30
1%
b1 5
b1 -
b1 4
1'
#35
0'
#40
0%
06
b10 4
1'
#45
0'
#50
1%
b11 4
1'
#55
0'
#60
0%
b100 4
1'
#65
0'
#70
1%
b101 4
1'
#75
0'
#80
0%
b110 4
1'
#85
0'
#90
1%
b111 4
1'
#95
0'
#100
0%
b1000 4
1'
#105
0'
#110
1%
b1001 4
1'
#115
0'
#120
0%
b1010 4
1'
#125
0'
#130
1%
b1011 4
1'
#135
0'
#140
0%
b1100 4
1'
#145
0'
#150
1%
b1101 4
1'
#155
0'
#160
0%
b1110 4
1'
#165
0'
#170
1%
b1111 4
1'
#175
0'
#180
0%
b10000000 ,
b10000 4
1'
#185
0'
#190
1%
b1 /
12
b10 -
b10001 4
1'
#195
0'
#200
0%
b10010 4
1'
#205
0'
#210
1%
b10 /
b10011 4
1'
#215
0'
#220
0%
b10100 4
1'
#225
0'
#230
1%
b100 /
b10101 4
1'
#235
0'
#240
0%
b10110 4
1'
#245
0'
#250
1%
b1000 /
b10111 4
1'
#255
0'
#260
0%
b11000 4
1'
#265
0'
#270
1%
b10000 /
b11001 4
1'
#275
0'
#280
0%
b11010 4
1'
#285
0'
#290
1%
b100000 /
b11011 4
1'
#295
0'
#300
0%
b11100 4
1'
#305
0'
#310
1%
b1000000 /
b11101 4
1'
#315
0'
#320
0%
b11110 4
1'
#325
0'
#330
1"
1%
b10000000 /
b11111 4
1'
#335
0'
#340
0%
b10110100 ,
b100000 4
1'
#345
0'
#350
0"
1%
02
b0 /
b10001001010101000100000 1
b0 -
b100001 4
1'
#355
0'
#360
b10001001010101000011111 1
1'
#365
0'
#370
b10001001010101000011110 1
1'
#375
0'
#380
b10001001010101000011101 1
1'
#385
0'
#390
b10001001010101000011100 1
1'
#395
0'
#400
b10001001010101000011011 1
1'
#405
0'
#410
b10001001010101000011010 1
1'
#415
0'
#420
b10001001010101000011001 1
1'
#425
0'
#430
b10001001010101000011000 1
1'
#435
0'
#440
b10001001010101000010111 1
1'
#445
0'
#450
b10001001010101000010110 1
1'
#455
0'
#460
b10001001010101000010101 1
1'
#465
0'
#470
b10001001010101000010100 1
1'
#475
0'
#480
b10001001010101000010011 1
1'
#485
0'
#490
b10001001010101000010010 1
1'
#495
0'
#500
b10001001010101000010001 1
1'
#505
0'
#510
b10001001010101000010000 1
1'
#515
0'
#520
b10001001010101000001111 1
1'
#525
0'
#530
b10001001010101000001110 1
1'
#535
0'
#540
b10001001010101000001101 1
1'
#545
0'
#550
b10001001010101000001100 1
1'
#555
0'
#560
b10001001010101000001011 1
1'
#565
0'
#570
b10001001010101000001010 1
1'
#575
0'
#580
b10001001010101000001001 1
1'
#585
0'
#590
b10001001010101000001000 1
1'
#595
0'
#600
b10001001010101000000111 1
1'
#605
0'
#610
b10001001010101000000110 1
1'
#615
0'
#620
b10001001010101000000101 1
1'
#625
0'
#630
b10001001010101000000100 1
1'
#635
0'
#640
b10001001010101000000011 1
1'
#645
0'
#650
b10001001010101000000010 1
1'
#655
0'
#660
b10001001010101000000001 1
1'
#665
0'
#670
b10001001010101000000000 1
1'
#675
0'
#680
b10001001010100111111111 1
1'
#685
0'
#690
b10001001010100111111110 1
1'
#695
0'
#700
b10001001010100111111101 1
1'
#705
0'
#710
b10001001010100111111100 1
1'
#715
0'
#720
b10001001010100111111011 1
1'
#725
0'
#730
b10001001010100111111010 1
1'
#735
0'
#740
b10001001010100111111001 1
1'
#745
0'
#750
b10001001010100111111000 1
1'
#755
0'
#760
b10001001010100111110111 1
1'
#765
0'
#770
b10001001010100111110110 1
1'
#775
0'
#780
b10001001010100111110101 1
1'
#785
0'
#790
b10001001010100111110100 1
1'
#795
0'
#800
b10001001010100111110011 1
1'
#805
0'
#810
b10001001010100111110010 1
1'
#815
0'
#820
b10001001010100111110001 1
1'
#825
0'
#830
b10001001010100111110000 1
1'
#835
0'
#840
b10001001010100111101111 1
1'
#845
0'
#850
b10001001010100111101110 1
1'
#855
0'
#860
b10001001010100111101101 1
1'
#865
0'
#870
b10001001010100111101100 1
1'
#875
0'
#880
b10001001010100111101011 1
1'
#885
0'
#890
b10001001010100111101010 1
1'
#895
0'
#900
b10001001010100111101001 1
1'
#905
0'
#910
b10001001010100111101000 1
1'
#915
0'
#920
b10001001010100111100111 1
1'
#925
0'
#930
b10001001010100111100110 1
1'
#935
0'
#940
b10001001010100111100101 1
1'
#945
0'
#950
b10001001010100111100100 1
1'
#955
0'
#960
b10001001010100111100011 1
1'
#965
0'
#970
b10001001010100111100010 1
1'
#975
0'
#980
b10001001010100111100001 1
1'
#985
0'
#990
b10001001010100111100000 1
1'
#995
0'
#1000
b10001001010100111011111 1
1'
#1005
0'
#1010
b10001001010100111011110 1
1'
#1015
0'
#1020
b10001001010100111011101 1
1'
#1025
0'
#1030
b10001001010100111011100 1
1'
#1035
0'
#1040
b10001001010100111011011 1
1'
#1045
0'
#1050
b10001001010100111011010 1
1'
#1055
0'
#1060
b10001001010100111011001 1
1'
#1065
0'
#1070
b10001001010100111011000 1
1'
#1075
0'
#1080
b10001001010100111010111 1
1'
#1085
0'
#1090
b10001001010100111010110 1
1'
#1095
0'
#1100
b10001001010100111010101 1
1'
#1105
0'
#1110
b10001001010100111010100 1
1'
#1115
0'
#1120
b10001001010100111010011 1
1'
#1125
0'
#1130
b10001001010100111010010 1
1'
#1135
0'
#1140
b10001001010100111010001 1
1'
#1145
0'
#1150
b10001001010100111010000 1
1'
#1155
0'
#1160
b10001001010100111001111 1
1'
#1165
0'
#1170
b10001001010100111001110 1
1'
#1175
0'
#1180
b10001001010100111001101 1
1'
#1185
0'
#1190
b10001001010100111001100 1
1'
#1195
0'
#1200
b10001001010100111001011 1
1'
#1205
0'
#1210
b10001001010100111001010 1
1'
#1215
0'
#1220
b10001001010100111001001 1
1'
#1225
0'
#1230
b10001001010100111001000 1
1'
#1235
0'
#1240
b10001001010100111000111 1
1'
#1245
0'
#1250
b10001001010100111000110 1
1'
#1255
0'
#1260
b10001001010100111000101 1
1'
#1265
0'
#1270
b10001001010100111000100 1
1'
#1275
0'
#1280
b10001001010100111000011 1
1'
#1285
0'
#1290
b10001001010100111000010 1
1'
#1295
0'
#1300
b10001001010100111000001 1
1'
#1305
0'
#1310
b10001001010100111000000 1
1'
#1315
0'
#1320
b10001001010100110111111 1
1'
#1325
0'
#1330
b10001001010100110111110 1
1'
#1335
0'
#1340
b10001001010100110111101 1
1'
#1345
0'
#1350
b10001001010100110111100 1
1'
#1355
0'
#1360
b10001001010100110111011 1
1'
#1365
0'
#1370
b10001001010100110111010 1
1'
#1375
0'
#1380
b10001001010100110111001 1
1'
#1385
0'
#1390
b10001001010100110111000 1
1'
#1395
0'
#1400
b10001001010100110110111 1
1'
#1405
0'
#1410
b10001001010100110110110 1
1'
#1415
0'
#1420
b10001001010100110110101 1
1'
#1425
0'
#1430
b10001001010100110110100 1
1'
#1435
0'
#1440
b10001001010100110110011 1
1'
#1445
0'
#1450
b10001001010100110110010 1
1'
#1455
0'
#1460
b10001001010100110110001 1
1'
#1465
0'
#1470
b10001001010100110110000 1
1'
#1475
0'
#1480
b10001001010100110101111 1
1'
#1485
0'
#1490
b10001001010100110101110 1
1'
#1495
0'
#1500
b10001001010100110101101 1
1'
#1505
0'
#1510
b10001001010100110101100 1
1'
#1515
0'
#1520
b10001001010100110101011 1
1'
#1525
0'
#1530
b10001001010100110101010 1
1'
#1535
0'
#1540
b10001001010100110101001 1
1'
#1545
0'
#1550
b10001001010100110101000 1
1'
#1555
0'
#1560
b10001001010100110100111 1
1'
#1565
0'
#1570
b10001001010100110100110 1
1'
#1575
0'
#1580
b10001001010100110100101 1
1'
#1585
0'
#1590
b10001001010100110100100 1
1'
#1595
0'
#1600
b10001001010100110100011 1
1'
#1605
0'
#1610
b10001001010100110100010 1
1'
#1615
0'
#1620
b10001001010100110100001 1
1'
#1625
0'
#1630
b10001001010100110100000 1
1'
#1635
0'
#1640
b10001001010100110011111 1
1'
#1645
0'
#1650
b10001001010100110011110 1
1'
#1655
0'
#1660
b10001001010100110011101 1
1'
#1665
0'
#1670
b10001001010100110011100 1
1'
#1675
0'
#1680
b10001001010100110011011 1
1'
#1685
0'
#1690
b10001001010100110011010 1
1'
#1695
0'
#1700
b10001001010100110011001 1
1'
#1705
0'
#1710
b10001001010100110011000 1
1'
#1715
0'
#1720
b10001001010100110010111 1
1'
#1725
0'
#1730
b10001001010100110010110 1
1'
#1735
0'
#1740
b10001001010100110010101 1
1'
#1745
0'
#1750
b10001001010100110010100 1
1'
#1755
0'
#1760
b10001001010100110010011 1
1'
#1765
0'
#1770
b10001001010100110010010 1
1'
#1775
0'
#1780
b10001001010100110010001 1
1'
#1785
0'
#1790
b10001001010100110010000 1
1'
#1795
0'
#1800
b10001001010100110001111 1
1'
#1805
0'
#1810
b10001001010100110001110 1
1'
#1815
0'
#1820
b10001001010100110001101 1
1'
#1825
0'
#1830
b10001001010100110001100 1
1'
#1835
0'
#1840
b10001001010100110001011 1
1'
#1845
0'
#1850
b10001001010100110001010 1
1'
#1855
0'
#1860
b10001001010100110001001 1
1'
#1865
0'
#1870
b10001001010100110001000 1
1'
#1875
0'
#1880
b10001001010100110000111 1
1'
#1885
0'
#1890
b10001001010100110000110 1
1'
#1895
0'
#1900
b10001001010100110000101 1
1'
#1905
0'
#1910
b10001001010100110000100 1
1'
#1915
0'
#1920
b10001001010100110000011 1
1'
#1925
0'
#1930
b10001001010100110000010 1
1'
#1935
0'
#1940
b10001001010100110000001 1
1'
#1945
0'
#1950
b10001001010100110000000 1
1'
#1955
0'
#1960
b10001001010100101111111 1
1'
#1965
0'
#1970
b10001001010100101111110 1
1'
#1975
0'
#1980
b10001001010100101111101 1
1'
#1985
0'
#1990
b10001001010100101111100 1
1'
#1995
0'
#2000
b10001001010100101111011 1
1'
#2005
0'
#2010
b10001001010100101111010 1
1'
#2015
0'
#2020
b10001001010100101111001 1
1'
#2025
0'
#2030
b10001001010100101111000 1
1'
#2035
0'
#2040
b10001001010100101110111 1
1'
#2045
0'
#2050
b10001001010100101110110 1
1'
#2055
0'
#2060
b10001001010100101110101 1
1'
#2065
0'
#2070
b10001001010100101110100 1
1'
#2075
0'
#2080
b10001001010100101110011 1
1'
#2085
0'
#2090
b10001001010100101110010 1
1'
#2095
0'
#2100
b10001001010100101110001 1
1'
#2105
0'
#2110
b10001001010100101110000 1
1'
#2115
0'
#2120
b10001001010100101101111 1
1'
#2125
0'
#2130
b10001001010100101101110 1
1'
#2135
0'
#2140
b10001001010100101101101 1
1'
#2145
0'
#2150
b10001001010100101101100 1
1'
#2155
0'
#2160
b10001001010100101101011 1
1'
#2165
0'
#2170
b10001001010100101101010 1
1'
#2175
0'
#2180
b10001001010100101101001 1
1'
#2185
0'
#2190
b10001001010100101101000 1
1'
#2195
0'
#2200
b10001001010100101100111 1
1'
#2205
0'
#2210
b10001001010100101100110 1
1'
#2215
0'
#2220
b10001001010100101100101 1
1'
#2225
0'
#2230
b10001001010100101100100 1
1'
#2235
0'
#2240
b10001001010100101100011 1
1'
#2245
0'
#2250
b10001001010100101100010 1
1'
#2255
0'
#2260
b10001001010100101100001 1
1'
#2265
0'
#2270
b10001001010100101100000 1
1'
#2275
0'
#2280
b10001001010100101011111 1
1'
#2285
0'
#2290
b10001001010100101011110 1
1'
#2295
0'
#2300
b10001001010100101011101 1
1'
#2305
0'
#2310
b10001001010100101011100 1
1'
#2315
0'
#2320
b10001001010100101011011 1
1'
#2325
0'
#2330
b10001001010100101011010 1
1'
#2335
0'
#2340
b10001001010100101011001 1
1'
#2345
0'
#2350
b10001001010100101011000 1
1'
#2355
0'
#2360
b10001001010100101010111 1
1'
#2365
0'
#2370
b10001001010100101010110 1
1'
#2375
0'
#2380
b10001001010100101010101 1
1'
#2385
0'
#2390
b10001001010100101010100 1
1'
#2395
0'
#2400
b10001001010100101010011 1
1'
#2405
0'
#2410
b10001001010100101010010 1
1'
#2415
0'
#2420
b10001001010100101010001 1
1'
#2425
0'
#2430
b10001001010100101010000 1
1'
#2435
0'
#2440
b10001001010100101001111 1
1'
#2445
0'
#2450
b10001001010100101001110 1
1'
#2455
0'
#2460
b10001001010100101001101 1
1'
#2465
0'
#2470
b10001001010100101001100 1
1'
#2475
0'
#2480
b10001001010100101001011 1
1'
#2485
0'
#2490
b10001001010100101001010 1
1'
#2495
0'
#2500
b10001001010100101001001 1
1'
#2505
0'
#2510
b10001001010100101001000 1
1'
#2515
0'
#2520
b10001001010100101000111 1
1'
#2525
0'
#2530
b10001001010100101000110 1
1'
#2535
0'
#2540
b10001001010100101000101 1
1'
#2545
0'
#2550
b10001001010100101000100 1
1'
#2555
0'
#2560
b10001001010100101000011 1
1'
#2565
0'
#2570
b10001001010100101000010 1
1'
#2575
0'
#2580
b10001001010100101000001 1
1'
#2585
0'
#2590
b10001001010100101000000 1
1'
#2595
0'
#2600
b10001001010100100111111 1
1'
#2605
0'
#2610
b10001001010100100111110 1
1'
#2615
0'
#2620
b10001001010100100111101 1
1'
#2625
0'
#2630
b10001001010100100111100 1
1'
#2635
0'
#2640
b10001001010100100111011 1
1'
#2645
0'
#2650
b10001001010100100111010 1
1'
#2655
0'
#2660
b10001001010100100111001 1
1'
#2665
0'
#2670
b10001001010100100111000 1
1'
#2675
0'
#2680
b10001001010100100110111 1
1'
#2685
0'
#2690
b10001001010100100110110 1
1'
#2695
0'
#2700
b10001001010100100110101 1
1'
#2705
0'
#2710
b10001001010100100110100 1
1'
#2715
0'
#2720
b10001001010100100110011 1
1'
#2725
0'
#2730
b10001001010100100110010 1
1'
#2735
0'
#2740
b10001001010100100110001 1
1'
#2745
0'
#2750
b10001001010100100110000 1
1'
#2755
0'
#2760
b10001001010100100101111 1
1'
#2765
0'
#2770
b10001001010100100101110 1
1'
#2775
0'
#2780
b10001001010100100101101 1
1'
#2785
0'
#2790
b10001001010100100101100 1
1'
#2795
0'
#2800
b10001001010100100101011 1
1'
#2805
0'
#2810
b10001001010100100101010 1
1'
#2815
0'
#2820
b10001001010100100101001 1
1'
#2825
0'
#2830
b10001001010100100101000 1
1'
#2835
0'
#2840
b10001001010100100100111 1
1'
#2845
0'
#2850
b10001001010100100100110 1
1'
#2855
0'
#2860
b10001001010100100100101 1
1'
#2865
0'
#2870
b10001001010100100100100 1
1'
#2875
0'
#2880
b10001001010100100100011 1
1'
#2885
0'
#2890
b10001001010100100100010 1
1'
#2895
0'
#2900
b10001001010100100100001 1
1'
#2905
0'
#2910
b10001001010100100100000 1
1'
#2915
0'
#2920
b10001001010100100011111 1
1'
#2925
0'
#2930
b10001001010100100011110 1
1'
#2935
0'
#2940
b10001001010100100011101 1
1'
#2945
0'
#2950
b10001001010100100011100 1
1'
#2955
0'
#2960
b10001001010100100011011 1
1'
#2965
0'
#2970
b10001001010100100011010 1
1'
#2975
0'
#2980
b10001001010100100011001 1
1'
#2985
0'
#2990
b10001001010100100011000 1
1'
#2995
0'
#3000
b10001001010100100010111 1
1'
#3005
0'
#3010
b10001001010100100010110 1
1'
#3015
0'
#3020
b10001001010100100010101 1
1'
#3025
0'
#3030
b10001001010100100010100 1
1'
#3035
0'
#3040
b10001001010100100010011 1
1'
#3045
0'
#3050
b10001001010100100010010 1
1'
#3055
0'
#3060
b10001001010100100010001 1
1'
#3065
0'
#3070
b10001001010100100010000 1
1'
#3075
0'
#3080
b10001001010100100001111 1
1'
#3085
0'
#3090
b10001001010100100001110 1
1'
#3095
0'
#3100
b10001001010100100001101 1
1'
#3105
0'
#3110
b10001001010100100001100 1
1'
#3115
0'
#3120
b10001001010100100001011 1
1'
#3125
0'
#3130
b10001001010100100001010 1
1'
#3135
0'
#3140
b10001001010100100001001 1
1'
#3145
0'
#3150
b10001001010100100001000 1
1'
#3155
0'
#3160
b10001001010100100000111 1
1'
#3165
0'
#3170
b10001001010100100000110 1
1'
#3175
0'
#3180
b10001001010100100000101 1
1'
#3185
0'
#3190
b10001001010100100000100 1
1'
#3195
0'
#3200
b10001001010100100000011 1
1'
#3205
0'
#3210
b10001001010100100000010 1
1'
#3215
0'
#3220
b10001001010100100000001 1
1'
#3225
0'
#3230
b10001001010100100000000 1
1'
#3235
0'
#3240
b10001001010100011111111 1
1'
#3245
0'
#3250
b10001001010100011111110 1
1'
#3255
0'
#3260
b10001001010100011111101 1
1'
#3265
0'
#3270
b10001001010100011111100 1
1'
#3275
0'
#3280
b10001001010100011111011 1
1'
#3285
0'
#3290
b10001001010100011111010 1
1'
#3295
0'
#3300
b10001001010100011111001 1
1'
#3305
0'
#3310
b10001001010100011111000 1
1'
#3315
0'
#3320
b10001001010100011110111 1
1'
#3325
0'
#3330
b10001001010100011110110 1
1'
#3335
0'
#3340
b10001001010100011110101 1
1'
#3345
0'
#3350
b10001001010100011110100 1
1'
#3355
0'
#3360
b10001001010100011110011 1
1'
#3365
0'
#3370
b10001001010100011110010 1
1'
#3375
0'
#3380
b10001001010100011110001 1
1'
#3385
0'
#3390
b10001001010100011110000 1
1'
#3395
0'
#3400
b10001001010100011101111 1
1'
#3405
0'
#3410
b10001001010100011101110 1
1'
#3415
0'
#3420
b10001001010100011101101 1
1'
#3425
0'
#3430
b10001001010100011101100 1
1'
#3435
0'
#3440
b10001001010100011101011 1
1'
#3445
0'
#3450
b10001001010100011101010 1
1'
#3455
0'
#3460
b10001001010100011101001 1
1'
#3465
0'
#3470
b10001001010100011101000 1
1'
#3475
0'
#3480
b10001001010100011100111 1
1'
#3485
0'
#3490
b10001001010100011100110 1
1'
#3495
0'
#3500
b10001001010100011100101 1
1'
#3505
0'
#3510
b10001001010100011100100 1
1'
#3515
0'
#3520
b10001001010100011100011 1
1'
#3525
0'
#3530
b10001001010100011100010 1
1'
#3535
0'
#3540
b10001001010100011100001 1
1'
#3545
0'
#3550
b10001001010100011100000 1
1'
#3555
0'
#3560
b10001001010100011011111 1
1'
#3565
0'
#3570
b10001001010100011011110 1
1'
#3575
0'
#3580
b10001001010100011011101 1
1'
#3585
0'
#3590
b10001001010100011011100 1
1'
#3595
0'
#3600
b10001001010100011011011 1
1'
#3605
0'
#3610
b10001001010100011011010 1
1'
#3615
0'
#3620
b10001001010100011011001 1
1'
#3625
0'
#3630
b10001001010100011011000 1
1'
#3635
0'
#3640
b10001001010100011010111 1
1'
#3645
0'
#3650
b10001001010100011010110 1
1'
#3655
0'
#3660
b10001001010100011010101 1
1'
#3665
0'
#3670
b10001001010100011010100 1
1'
#3675
0'
#3680
b10001001010100011010011 1
1'
#3685
0'
#3690
b10001001010100011010010 1
1'
#3695
0'
#3700
b10001001010100011010001 1
1'
#3705
0'
#3710
b10001001010100011010000 1
1'
#3715
0'
#3720
b10001001010100011001111 1
1'
#3725
0'
#3730
b10001001010100011001110 1
1'
#3735
0'
#3740
b10001001010100011001101 1
1'
#3745
0'
#3750
b10001001010100011001100 1
1'
#3755
0'
#3760
b10001001010100011001011 1
1'
#3765
0'
#3770
b10001001010100011001010 1
1'
#3775
0'
#3780
b10001001010100011001001 1
1'
#3785
0'
#3790
b10001001010100011001000 1
1'
#3795
0'
#3800
b10001001010100011000111 1
1'
#3805
0'
#3810
b10001001010100011000110 1
1'
#3815
0'
#3820
b10001001010100011000101 1
1'
#3825
0'
#3830
b10001001010100011000100 1
1'
#3835
0'
#3840
b10001001010100011000011 1
1'
#3845
0'
#3850
b10001001010100011000010 1
1'
#3855
0'
#3860
b10001001010100011000001 1
1'
#3865
0'
#3870
b10001001010100011000000 1
1'
#3875
0'
#3880
b10001001010100010111111 1
1'
#3885
0'
#3890
b10001001010100010111110 1
1'
#3895
0'
#3900
b10001001010100010111101 1
1'
#3905
0'
#3910
b10001001010100010111100 1
1'
#3915
0'
#3920
b10001001010100010111011 1
1'
#3925
0'
#3930
b10001001010100010111010 1
1'
#3935
0'
#3940
b10001001010100010111001 1
1'
#3945
0'
#3950
b10001001010100010111000 1
1'
#3955
0'
#3960
b10001001010100010110111 1
1'
#3965
0'
#3970
b10001001010100010110110 1
1'
#3975
0'
#3980
b10001001010100010110101 1
1'
#3985
0'
#3990
b10001001010100010110100 1
1'
#3995
0'
#4000
b10001001010100010110011 1
1'
#4005
0'
#4010
b10001001010100010110010 1
1'
#4015
0'
#4020
b10001001010100010110001 1
1'
#4025
0'
#4030
b10001001010100010110000 1
1'
#4035
0'
#4040
b10001001010100010101111 1
1'
#4045
0'
#4050
b10001001010100010101110 1
1'
#4055
0'
#4060
b10001001010100010101101 1
1'
#4065
0'
#4070
b10001001010100010101100 1
1'
#4075
0'
#4080
b10001001010100010101011 1
1'
#4085
0'
#4090
b10001001010100010101010 1
1'
#4095
0'
#4100
b10001001010100010101001 1
1'
#4105
0'
#4110
b10001001010100010101000 1
1'
#4115
0'
#4120
b10001001010100010100111 1
1'
#4125
0'
#4130
b10001001010100010100110 1
1'
#4135
0'
#4140
b10001001010100010100101 1
1'
#4145
0'
#4150
b10001001010100010100100 1
1'
#4155
0'
#4160
b10001001010100010100011 1
1'
#4165
0'
#4170
b10001001010100010100010 1
1'
#4175
0'
#4180
b10001001010100010100001 1
1'
#4185
0'
#4190
b10001001010100010100000 1
1'
#4195
0'
#4200
b10001001010100010011111 1
1'
#4205
0'
#4210
b10001001010100010011110 1
1'
#4215
0'
#4220
b10001001010100010011101 1
1'
#4225
0'
#4230
b10001001010100010011100 1
1'
#4235
0'
#4240
b10001001010100010011011 1
1'
#4245
0'
#4250
b10001001010100010011010 1
1'
#4255
0'
#4260
b10001001010100010011001 1
1'
#4265
0'
#4270
b10001001010100010011000 1
1'
#4275
0'
#4280
b10001001010100010010111 1
1'
#4285
0'
#4290
b10001001010100010010110 1
1'
#4295
0'
#4300
b10001001010100010010101 1
1'
#4305
0'
#4310
b10001001010100010010100 1
1'
#4315
0'
#4320
b10001001010100010010011 1
1'
#4325
0'
#4330
b10001001010100010010010 1
1'
#4335
0'
#4340
b10001001010100010010001 1
1'
#4345
0'
#4350
b10001001010100010010000 1
1'
#4355
0'
#4360
b10001001010100010001111 1
1'
#4365
0'
#4370
b10001001010100010001110 1
1'
#4375
0'
#4380
b10001001010100010001101 1
1'
#4385
0'
#4390
b10001001010100010001100 1
1'
#4395
0'
#4400
b10001001010100010001011 1
1'
#4405
0'
#4410
b10001001010100010001010 1
1'
#4415
0'
#4420
b10001001010100010001001 1
1'
#4425
0'
#4430
b10001001010100010001000 1
1'
#4435
0'
#4440
b10001001010100010000111 1
1'
#4445
0'
#4450
b10001001010100010000110 1
1'
#4455
0'
#4460
b10001001010100010000101 1
1'
#4465
0'
#4470
b10001001010100010000100 1
1'
#4475
0'
#4480
b10001001010100010000011 1
1'
#4485
0'
#4490
b10001001010100010000010 1
1'
#4495
0'
#4500
b10001001010100010000001 1
1'
#4505
0'
#4510
b10001001010100010000000 1
1'
#4515
0'
#4520
b10001001010100001111111 1
1'
#4525
0'
#4530
b10001001010100001111110 1
1'
#4535
0'
#4540
b10001001010100001111101 1
1'
#4545
0'
#4550
b10001001010100001111100 1
1'
#4555
0'
#4560
b10001001010100001111011 1
1'
#4565
0'
#4570
b10001001010100001111010 1
1'
#4575
0'
#4580
b10001001010100001111001 1
1'
#4585
0'
#4590
b10001001010100001111000 1
1'
#4595
0'
